sphinxcontrib_programoutput_rai-0.18.dev0-py3.12-nspkg.pth
sphinxcontrib/programoutput/__init__.py
sphinxcontrib/programoutput/tests/__init__.py
sphinxcontrib/programoutput/tests/test_cache.py
sphinxcontrib/programoutput/tests/test_command.py
sphinxcontrib/programoutput/tests/test_directive.py
sphinxcontrib/programoutput/tests/test_setup.py
sphinxcontrib/programoutput/tests/test_util.py
sphinxcontrib_programoutput_rai-0.18.dev0.dist-info/licenses/LICENSE
sphinxcontrib_programoutput_rai-0.18.dev0.dist-info/METADATA
sphinxcontrib_programoutput_rai-0.18.dev0.dist-info/WHEEL
sphinxcontrib_programoutput_rai-0.18.dev0.dist-info/namespace_packages.txt
sphinxcontrib_programoutput_rai-0.18.dev0.dist-info/top_level.txt
sphinxcontrib_programoutput_rai-0.18.dev0.dist-info/RECORD
